README.rst
setup.py
convertx/__init__.py
convertx/cli.py
convertx/styles.py
convertx.egg-info/PKG-INFO
convertx.egg-info/SOURCES.txt
convertx.egg-info/dependency_links.txt
convertx.egg-info/entry_points.txt
convertx.egg-info/requires.txt
convertx.egg-info/top_level.txt