Metadata-Version: 1.2
Name: convertx
Version: 0.1
Summary: Convert Word documents (docx) to clean HTML and Markdown
Home-page: http://github.com/VolkerBergen/convertx
Author: Volker Bergen
Author-email: email@volkerbergen.de
License: BSD-2-Clause
Keywords: docx word clean html markdown md
Platform: UNKNOWN
Classifier: License :: OSI Approved :: BSD License
Classifier: Development Status :: 5 - Production/Stable
Classifier: Intended Audience :: Developers
Classifier: Programming Language :: Python
Requires-Python: >=2.7
